klarify/Kustomizer.py
klarify/Parser.py
klarify/Resource.py
klarify/Sorter.py
klarify/__init__.py
klarify/__main__.py
klarify-0.0.1.dist-info/LICENSE
klarify-0.0.1.dist-info/METADATA
klarify-0.0.1.dist-info/WHEEL
klarify-0.0.1.dist-info/entry_points.txt
klarify-0.0.1.dist-info/top_level.txt
klarify-0.0.1.dist-info/RECORD
