Metadata-Version: 2.1
Name: klarify
Version: 0.0.1
Summary: Automatic sort and separate for multi-yaml files
Home-page: https://github.com/thetalorian/klarify
Author: Samuel Plum
Author-email: psyborg@taloria.com
License: UNKNOWN
Project-URL: Bug Tracker, https://github.com/thetalorian/klarify/issues
Platform: UNKNOWN
Classifier: Programming Language :: Python :: 3
Classifier: License :: OSI Approved :: MIT License
Classifier: Operating System :: OS Independent
Requires-Python: >=3.6
License-File: LICENSE
